bytecodes/__init__.py
bytecodes/func.py
bytecodes/insn.py
bytecodes/test.py
bytecodes-0.0.1a2.dist-info/LICENSE
bytecodes-0.0.1a2.dist-info/METADATA
bytecodes-0.0.1a2.dist-info/WHEEL
bytecodes-0.0.1a2.dist-info/top_level.txt
bytecodes-0.0.1a2.dist-info/RECORD
