Metadata-Version: 2.1
Name: bytecodes
Version: 0.0.1a2
Summary: 修改函数中的一切！/Change everything in a function!
Home-page: UNKNOWN
Author: 方南承/Steven Jackson Fang
Author-email: UNKNOWN
License: UNKNOWN
Platform: UNKNOWN
Classifier: Development Status :: 2 - Pre-Alpha
Classifier: Intended Audience :: Developers
Classifier: License :: OSI Approved :: MIT License
Classifier: Natural Language :: Chinese (Simplified)
Classifier: Natural Language :: English
Classifier: Programming Language :: Python :: 3.8
